ufjc/__init__.py
ufjc/core.py
ufjc/isometric.py
ufjc/isotensional.py
ufjc/monte_carlo.py
ufjc/potential.py
ufjc/swfjc.py
ufjc/utility.py
ufjc/examples/__init__.py
ufjc/examples/__main__.py
ufjc/examples/approaches.py
ufjc/examples/asymptotics.py
ufjc/examples/error.py
ufjc/tests/__init__.py
ufjc/tests/__main__.py
ufjc/tests/test_examples.py
ufjc/tests/test_style.py
ufjc-1.3.6.dist-info/LICENSE
ufjc-1.3.6.dist-info/METADATA
ufjc-1.3.6.dist-info/WHEEL
ufjc-1.3.6.dist-info/top_level.txt
ufjc-1.3.6.dist-info/RECORD
