Metadata-Version: 2.1
Name: ufjc
Version: 1.3.6
Summary: The Python package for the uFJC single-chain model.
Home-page: https://sandialabs.github.io/uFJC
Author: Michael R. Buche, Scott J. Grutzik
Author-email: mrbuche@sandia.gov, sjgrutz@sandia.gov
License: BSD-3-Clause
Project-URL: Anaconda, https://anaconda.org/mrbuche/ufjc
Project-URL: Documentation, https://ufjc.readthedocs.io
Project-URL: GitHub, https://github.com/sandialabs/ufjc
Project-URL: Issues, https://github.com/sandialabs/ufjc/issues
Keywords: ufjc,polymers,statistical mechanics,thermodynamics
Classifier: License :: OSI Approved :: BSD License
Classifier: Development Status :: 5 - Production/Stable
Classifier: Intended Audience :: Science/Research
Classifier: Topic :: Scientific/Engineering
Classifier: Programming Language :: Python :: 3.5
Classifier: Programming Language :: Python :: 3.6
Classifier: Programming Language :: Python :: 3.7
Classifier: Programming Language :: Python :: 3.8
Classifier: Programming Language :: Python :: 3.9
Classifier: Programming Language :: Python :: 3.10
License-File: LICENSE
Requires-Dist: numpy
Requires-Dist: pycodestyle
Requires-Dist: scipy
Provides-Extra: all
Requires-Dist: matplotlib ; extra == 'all'
Requires-Dist: pytest ; extra == 'all'
Requires-Dist: pytest-cov ; extra == 'all'
Requires-Dist: sphinx ; extra == 'all'
Requires-Dist: sphinx-copybutton ; extra == 'all'
Requires-Dist: sphinx-rtd-theme ; extra == 'all'
Requires-Dist: sphinxcontrib-bibtex ; extra == 'all'
Provides-Extra: docs
Requires-Dist: matplotlib ; extra == 'docs'
Requires-Dist: sphinx ; extra == 'docs'
Requires-Dist: sphinx-copybutton ; extra == 'docs'
Requires-Dist: sphinx-rtd-theme ; extra == 'docs'
Requires-Dist: sphinxcontrib-bibtex ; extra == 'docs'
Provides-Extra: plotting
Requires-Dist: matplotlib ; extra == 'plotting'
Provides-Extra: testing
Requires-Dist: matplotlib ; extra == 'testing'
Requires-Dist: pytest ; extra == 'testing'
Requires-Dist: pytest-cov ; extra == 'testing'
